<archimate:ArchimateDiagramModel
    xmlns:xsi="http://www.w3.org/2001/XMLSchema-instance"
    xmlns:archimate="http://www.archimatetool.com/archimate"
    name="04. Enterprise business function usage of CRM application functions"
    id="7830">
  <children
      xsi:type="archimate:DiagramModelArchimateObject"
      id="7839">
    <bounds
        x="160"
        y="266"
        width="720"
        height="160"/>
    <children
        xsi:type="archimate:DiagramModelArchimateObject"
        id="7841">
      <sourceConnections
          xsi:type="archimate:DiagramModelArchimateConnection"
          id="7847"
          font="1|Arial|12.0|0|WINDOWS|1|0|0|0|0|0|0|0|0|1|0|0|0|0|Arial"
          source="7841"
          target="7845">
        <archimateRelationship
            xsi:type="archimate:ServingRelationship"
            href="ServingRelationship_7826.xml#7826"/>
      </sourceConnections>
      <bounds
          x="33"
          y="53"
          width="133"
          height="53"/>
      <archimateElement
          xsi:type="archimate:ApplicationFunction"
          href="ApplicationFunction_7373.xml#7373"/>
    </children>
    <children
        xsi:type="archimate:DiagramModelArchimateObject"
        id="7843">
      <sourceConnections
          xsi:type="archimate:DiagramModelArchimateConnection"
          id="7848"
          font="1|Arial|12.0|0|WINDOWS|1|0|0|0|0|0|0|0|0|1|0|0|0|0|Arial"
          source="7843"
          target="7846">
        <archimateRelationship
            xsi:type="archimate:ServingRelationship"
            href="ServingRelationship_7827.xml#7827"/>
      </sourceConnections>
      <bounds
          x="560"
          y="53"
          width="133"
          height="53"/>
      <archimateElement
          xsi:type="archimate:ApplicationFunction"
          href="ApplicationFunction_7375.xml#7375"/>
    </children>
    <children
        xsi:type="archimate:DiagramModelArchimateObject"
        id="7844">
      <sourceConnections
          xsi:type="archimate:DiagramModelArchimateConnection"
          id="7849"
          font="1|Arial|12.0|0|WINDOWS|1|0|0|0|0|0|0|0|0|1|0|0|0|0|Arial"
          source="7844"
          target="7845">
        <archimateRelationship
            xsi:type="archimate:ServingRelationship"
            href="ServingRelationship_7836.xml#7836"/>
      </sourceConnections>
      <sourceConnections
          xsi:type="archimate:DiagramModelArchimateConnection"
          id="7891"
          font="1|Arial|12.0|0|WINDOWS|1|0|0|0|0|0|0|0|0|1|0|0|0|0|Arial"
          source="7844"
          target="7846">
        <archimateRelationship
            xsi:type="archimate:ServingRelationship"
            href="ServingRelationship_7889.xml#7889"/>
      </sourceConnections>
      <bounds
          x="293"
          y="53"
          width="133"
          height="53"/>
      <archimateElement
          xsi:type="archimate:ApplicationFunction"
          href="ApplicationFunction_7376.xml#7376"/>
    </children>
    <archimateElement
        xsi:type="archimate:ApplicationFunction"
        href="ApplicationFunction_7372.xml#7372"/>
  </children>
  <children
      xsi:type="archimate:DiagramModelArchimateObject"
      id="7845"
      targetConnections="7847 7849"
      fillColor="#ff8040">
    <bounds
        x="192"
        y="180"
        width="133"
        height="53"/>
    <archimateElement
        xsi:type="archimate:BusinessFunction"
        href="BusinessFunction_6188.xml#6188"/>
  </children>
  <children
      xsi:type="archimate:DiagramModelArchimateObject"
      id="7846"
      targetConnections="7848 7891"
      fillColor="#ff8080">
    <bounds
        x="720"
        y="180"
        width="133"
        height="53"/>
    <archimateElement
        xsi:type="archimate:BusinessFunction"
        href="BusinessFunction_6187.xml#6187"/>
  </children>
  <children
      xsi:type="archimate:DiagramModelNote"
      id="7893"
      font="1|Segoe UI|20.25|0|WINDOWS|1|-27|0|0|0|400|0|0|0|0|3|2|1|34|Segoe UI"
      content="Enterprise Business Function Usage of CRM Application Functions">
    <bounds
        x="174"
        y="36"
        width="691"
        height="88"/>
  </children>
</archimate:ArchimateDiagramModel>
