<archimate:ArchimateDiagramModel
    xmlns:xsi="http://www.w3.org/2001/XMLSchema-instance"
    xmlns:archimate="http://www.archimatetool.com/archimate"
    name="07. Object model summary"
    id="7924"
    viewpoint="11">
  <children
      xsi:type="archimate:DiagramModelArchimateObject"
      id="8012"
      targetConnections="8101">
    <sourceConnections
        xsi:type="archimate:DiagramModelArchimateConnection"
        id="8029"
        source="8012"
        target="8017">
      <archimateRelationship
          xsi:type="archimate:AggregationRelationship"
          href="AggregationRelationship_8004.xml#8004"/>
    </sourceConnections>
    <sourceConnections
        xsi:type="archimate:DiagramModelArchimateConnection"
        id="8100"
        source="8012"
        target="8011">
      <archimateRelationship
          xsi:type="archimate:AssociationRelationship"
          href="AssociationRelationship_8081.xml#8081"/>
    </sourceConnections>
    <sourceConnections
        xsi:type="archimate:DiagramModelArchimateConnection"
        id="8089"
        source="8012"
        target="7957">
      <archimateRelationship
          xsi:type="archimate:RealizationRelationship"
          href="RealizationRelationship_8072.xml#8072"/>
    </sourceConnections>
    <bounds
        x="233"
        y="409"
        width="133"
        height="75"/>
    <archimateElement
        xsi:type="archimate:DataObject"
        href="DataObject_7992.xml#7992"/>
  </children>
  <children
      xsi:type="archimate:DiagramModelArchimateObject"
      id="8013"
      targetConnections="8102">
    <sourceConnections
        xsi:type="archimate:DiagramModelArchimateConnection"
        id="8090"
        source="8013"
        target="7958">
      <archimateRelationship
          xsi:type="archimate:RealizationRelationship"
          href="RealizationRelationship_8073.xml#8073"/>
    </sourceConnections>
    <sourceConnections
        xsi:type="archimate:DiagramModelArchimateConnection"
        id="8101"
        source="8013"
        target="8012">
      <archimateRelationship
          xsi:type="archimate:AssociationRelationship"
          href="AssociationRelationship_8082.xml#8082"/>
    </sourceConnections>
    <sourceConnections
        xsi:type="archimate:DiagramModelArchimateConnection"
        id="8028"
        source="8013"
        target="8018">
      <archimateRelationship
          xsi:type="archimate:AggregationRelationship"
          href="AggregationRelationship_8003.xml#8003"/>
    </sourceConnections>
    <bounds
        x="393"
        y="413"
        width="133"
        height="68"/>
    <archimateElement
        xsi:type="archimate:DataObject"
        href="DataObject_7993.xml#7993"/>
  </children>
  <children
      xsi:type="archimate:DiagramModelArchimateObject"
      id="8014"
      targetConnections="8093">
    <sourceConnections
        xsi:type="archimate:DiagramModelArchimateConnection"
        id="8027"
        source="8014"
        target="8019">
      <archimateRelationship
          xsi:type="archimate:AggregationRelationship"
          href="AggregationRelationship_8002.xml#8002"/>
    </sourceConnections>
    <sourceConnections
        xsi:type="archimate:DiagramModelArchimateConnection"
        id="8091"
        source="8014"
        target="7959">
      <archimateRelationship
          xsi:type="archimate:RealizationRelationship"
          href="RealizationRelationship_8074.xml#8074"/>
    </sourceConnections>
    <sourceConnections
        xsi:type="archimate:DiagramModelArchimateConnection"
        id="8102"
        source="8014"
        target="8013">
      <archimateRelationship
          xsi:type="archimate:AssociationRelationship"
          href="AssociationRelationship_8083.xml#8083"/>
    </sourceConnections>
    <bounds
        x="566"
        y="413"
        width="133"
        height="68"/>
    <archimateElement
        xsi:type="archimate:DataObject"
        href="DataObject_7994.xml#7994"/>
  </children>
  <children
      xsi:type="archimate:DiagramModelArchimateObject"
      id="8015">
    <sourceConnections
        xsi:type="archimate:DiagramModelArchimateConnection"
        id="8093"
        source="8015"
        target="8014">
      <archimateRelationship
          xsi:type="archimate:AssociationRelationship"
          href="AssociationRelationship_8076.xml#8076"/>
    </sourceConnections>
    <sourceConnections
        xsi:type="archimate:DiagramModelArchimateConnection"
        id="8092"
        source="8015"
        target="7960">
      <archimateRelationship
          xsi:type="archimate:RealizationRelationship"
          href="RealizationRelationship_8075.xml#8075"/>
    </sourceConnections>
    <sourceConnections
        xsi:type="archimate:DiagramModelArchimateConnection"
        id="8023"
        source="8015"
        target="8020">
      <archimateRelationship
          xsi:type="archimate:AggregationRelationship"
          href="AggregationRelationship_8001.xml#8001"/>
    </sourceConnections>
    <bounds
        x="740"
        y="413"
        width="133"
        height="68"/>
    <archimateElement
        xsi:type="archimate:DataObject"
        href="DataObject_7995.xml#7995"/>
  </children>
  <children
      xsi:type="archimate:DiagramModelArchimateObject"
      id="8016"
      targetConnections="8099 8030">
    <bounds
        x="60"
        y="506"
        width="133"
        height="71"/>
    <archimateElement
        xsi:type="archimate:DataObject"
        href="DataObject_7996.xml#7996"/>
  </children>
  <children
      xsi:type="archimate:DiagramModelArchimateObject"
      id="8017"
      targetConnections="8029 8098">
    <sourceConnections
        xsi:type="archimate:DiagramModelArchimateConnection"
        id="8099"
        source="8017"
        target="8016">
      <archimateRelationship
          xsi:type="archimate:AssociationRelationship"
          href="AssociationRelationship_8080.xml#8080"/>
    </sourceConnections>
    <bounds
        x="233"
        y="506"
        width="133"
        height="71"/>
    <archimateElement
        xsi:type="archimate:DataObject"
        href="DataObject_7997.xml#7997"/>
  </children>
  <children
      xsi:type="archimate:DiagramModelArchimateObject"
      id="8018"
      targetConnections="8097 8028">
    <sourceConnections
        xsi:type="archimate:DiagramModelArchimateConnection"
        id="8098"
        source="8018"
        target="8017">
      <archimateRelationship
          xsi:type="archimate:AssociationRelationship"
          href="AssociationRelationship_8079.xml#8079"/>
    </sourceConnections>
    <bounds
        x="393"
        y="506"
        width="133"
        height="71"/>
    <archimateElement
        xsi:type="archimate:DataObject"
        href="DataObject_7998.xml#7998"/>
  </children>
  <children
      xsi:type="archimate:DiagramModelArchimateObject"
      id="8019"
      targetConnections="8027 8096">
    <sourceConnections
        xsi:type="archimate:DiagramModelArchimateConnection"
        id="8097"
        source="8019"
        target="8018">
      <archimateRelationship
          xsi:type="archimate:AssociationRelationship"
          href="AssociationRelationship_8078.xml#8078"/>
    </sourceConnections>
    <bounds
        x="566"
        y="506"
        width="133"
        height="71"/>
    <archimateElement
        xsi:type="archimate:DataObject"
        href="DataObject_7999.xml#7999"/>
  </children>
  <children
      xsi:type="archimate:DiagramModelArchimateObject"
      id="8020"
      targetConnections="8023">
    <sourceConnections
        xsi:type="archimate:DiagramModelArchimateConnection"
        id="8096"
        source="8020"
        target="8019">
      <archimateRelationship
          xsi:type="archimate:AssociationRelationship"
          href="AssociationRelationship_8077.xml#8077"/>
    </sourceConnections>
    <bounds
        x="740"
        y="506"
        width="133"
        height="71"/>
    <archimateElement
        xsi:type="archimate:DataObject"
        href="DataObject_8000.xml#8000"/>
  </children>
  <children
      xsi:type="archimate:DiagramModelArchimateObject"
      id="7951">
    <sourceConnections
        xsi:type="archimate:DiagramModelArchimateConnection"
        id="8024"
        source="7951"
        target="7954">
      <archimateRelationship
          xsi:type="archimate:AggregationRelationship"
          href="AggregationRelationship_8008.xml#8008"/>
    </sourceConnections>
    <bounds
        x="566"
        y="133"
        width="133"
        height="53"/>
    <archimateElement
        xsi:type="archimate:BusinessObject"
        href="BusinessObject_7940.xml#7940"/>
  </children>
  <children
      xsi:type="archimate:DiagramModelArchimateObject"
      id="7952">
    <sourceConnections
        xsi:type="archimate:DiagramModelArchimateConnection"
        id="8021"
        source="7952"
        target="7955">
      <archimateRelationship
          xsi:type="archimate:AggregationRelationship"
          href="AggregationRelationship_8006.xml#8006"/>
    </sourceConnections>
    <bounds
        x="746"
        y="133"
        width="133"
        height="53"/>
    <archimateElement
        xsi:type="archimate:BusinessObject"
        href="BusinessObject_7941.xml#7941"/>
  </children>
  <children
      xsi:type="archimate:DiagramModelArchimateObject"
      id="7953">
    <sourceConnections
        xsi:type="archimate:DiagramModelArchimateConnection"
        id="8026"
        source="7953"
        target="7958">
      <archimateRelationship
          xsi:type="archimate:AggregationRelationship"
          href="AggregationRelationship_8010.xml#8010"/>
    </sourceConnections>
    <bounds
        x="393"
        y="220"
        width="133"
        height="53"/>
    <archimateElement
        xsi:type="archimate:BusinessObject"
        href="BusinessObject_7942.xml#7942"/>
  </children>
  <children
      xsi:type="archimate:DiagramModelArchimateObject"
      id="7954"
      targetConnections="8095 8024">
    <sourceConnections
        xsi:type="archimate:DiagramModelArchimateConnection"
        id="8025"
        source="7954"
        target="7959">
      <archimateRelationship
          xsi:type="archimate:AggregationRelationship"
          href="AggregationRelationship_8009.xml#8009"/>
    </sourceConnections>
    <bounds
        x="566"
        y="220"
        width="133"
        height="53"/>
    <archimateElement
        xsi:type="archimate:BusinessObject"
        href="BusinessObject_7943.xml#7943"/>
  </children>
  <children
      xsi:type="archimate:DiagramModelArchimateObject"
      id="7955"
      targetConnections="8021">
    <sourceConnections
        xsi:type="archimate:DiagramModelArchimateConnection"
        id="8022"
        source="7955"
        target="7960">
      <archimateRelationship
          xsi:type="archimate:AggregationRelationship"
          href="AggregationRelationship_8007.xml#8007"/>
    </sourceConnections>
    <sourceConnections
        xsi:type="archimate:DiagramModelArchimateConnection"
        id="8095"
        source="7955"
        target="7954">
      <archimateRelationship
          xsi:type="archimate:AssociationRelationship"
          href="AssociationRelationship_8085.xml#8085"/>
    </sourceConnections>
    <bounds
        x="746"
        y="220"
        width="133"
        height="53"/>
    <archimateElement
        xsi:type="archimate:BusinessObject"
        href="BusinessObject_7944.xml#7944"/>
  </children>
  <children
      xsi:type="archimate:DiagramModelArchimateObject"
      id="7956"
      targetConnections="8088">
    <bounds
        x="60"
        y="306"
        width="133"
        height="53"/>
    <archimateElement
        xsi:type="archimate:BusinessObject"
        href="BusinessObject_7945.xml#7945"/>
  </children>
  <children
      xsi:type="archimate:DiagramModelArchimateObject"
      id="7957"
      targetConnections="8104 8089">
    <bounds
        x="233"
        y="306"
        width="133"
        height="60"/>
    <archimateElement
        xsi:type="archimate:BusinessObject"
        href="BusinessObject_7946.xml#7946"/>
  </children>
  <children
      xsi:type="archimate:DiagramModelArchimateObject"
      id="7958"
      targetConnections="8090 8103 8026">
    <sourceConnections
        xsi:type="archimate:DiagramModelArchimateConnection"
        id="8104"
        source="7958"
        target="7957">
      <archimateRelationship
          xsi:type="archimate:AssociationRelationship"
          href="AssociationRelationship_8087.xml#8087"/>
    </sourceConnections>
    <bounds
        x="393"
        y="306"
        width="133"
        height="53"/>
    <archimateElement
        xsi:type="archimate:BusinessObject"
        href="BusinessObject_7947.xml#7947"/>
  </children>
  <children
      xsi:type="archimate:DiagramModelArchimateObject"
      id="7959"
      targetConnections="8094 8025 8091">
    <sourceConnections
        xsi:type="archimate:DiagramModelArchimateConnection"
        id="8103"
        source="7959"
        target="7958">
      <archimateRelationship
          xsi:type="archimate:AssociationRelationship"
          href="AssociationRelationship_8086.xml#8086"/>
    </sourceConnections>
    <bounds
        x="566"
        y="306"
        width="133"
        height="53"/>
    <archimateElement
        xsi:type="archimate:BusinessObject"
        href="BusinessObject_7948.xml#7948"/>
  </children>
  <children
      xsi:type="archimate:DiagramModelArchimateObject"
      id="7960"
      targetConnections="8022 8092">
    <sourceConnections
        xsi:type="archimate:DiagramModelArchimateConnection"
        id="8094"
        source="7960"
        target="7959">
      <archimateRelationship
          xsi:type="archimate:AssociationRelationship"
          href="AssociationRelationship_8084.xml#8084"/>
    </sourceConnections>
    <bounds
        x="740"
        y="306"
        width="133"
        height="53"/>
    <archimateElement
        xsi:type="archimate:BusinessObject"
        href="BusinessObject_7949.xml#7949"/>
  </children>
  <children
      xsi:type="archimate:DiagramModelArchimateObject"
      id="8011"
      targetConnections="8100">
    <sourceConnections
        xsi:type="archimate:DiagramModelArchimateConnection"
        id="8088"
        source="8011"
        target="7956">
      <archimateRelationship
          xsi:type="archimate:RealizationRelationship"
          href="RealizationRelationship_8071.xml#8071"/>
    </sourceConnections>
    <sourceConnections
        xsi:type="archimate:DiagramModelArchimateConnection"
        id="8030"
        source="8011"
        target="8016">
      <archimateRelationship
          xsi:type="archimate:AggregationRelationship"
          href="AggregationRelationship_8005.xml#8005"/>
    </sourceConnections>
    <bounds
        x="60"
        y="413"
        width="133"
        height="68"/>
    <archimateElement
        xsi:type="archimate:DataObject"
        href="DataObject_7991.xml#7991"/>
  </children>
  <children
      xsi:type="archimate:DiagramModelNote"
      id="7926"
      font="1|Segoe UI|20.25|0|WINDOWS|1|-27|0|0|0|400|0|0|0|0|3|2|1|34|Segoe UI"
      content="Object Model Summary">
    <bounds
        x="216"
        y="36"
        width="466"
        height="47"/>
  </children>
  <children
      xsi:type="archimate:DiagramModelNote"
      id="7927"
      textAlignment="1"
      fillColor="#ffffc8"
      content="Based on ISA-95 Part I Figure 24, page 77&#xD;&#xA;All associations can be interpreted as right-to-left &quot;Corresponds to a...&quot; relation">
    <bounds
        x="66"
        y="126"
        width="186"
        height="102"/>
  </children>
</archimate:ArchimateDiagramModel>
